fast_torch
