Metadata-Version: 2.1
Name: fast-torch
Version: 1.2.1
Summary: Library that implements boiler plate code in PyTorch for training, testing and plotting your model
Home-page: https://github.com/YnsOzt/FastTorch
Author: Sakir Ozturk
Author-email: ozturk213@hotmail.fr
License: MIT
Keywords: PyTorch,boiler_plate,Train,Test,Plot
Platform: UNKNOWN
